LICENSE.txt
README.md
setup.cfg
setup.py
dl2050utils/__config__.py
dl2050utils/__init__.py
dl2050utils/__version__.py
dl2050utils/api.py
dl2050utils/auth.py
dl2050utils/com.py
dl2050utils/common.py
dl2050utils/core.py
dl2050utils/db copy.py
dl2050utils/db.py
dl2050utils/dbdf.py
dl2050utils/dbutils.py
dl2050utils/df.py
dl2050utils/env.py
dl2050utils/etl.py
dl2050utils/fdb.py
dl2050utils/fs.py
dl2050utils/graphql.py
dl2050utils/gs.py
dl2050utils/ju.py
dl2050utils/log.py
dl2050utils/mq.py
dl2050utils/rest.py
dl2050utils/restapp.py
dl2050utils/restutils.py
dl2050utils/sqlite.py
dl2050utils/ulists.py
dl2050utils/wsgi.py
dl2050utils.egg-info/PKG-INFO
dl2050utils.egg-info/SOURCES.txt
dl2050utils.egg-info/dependency_links.txt
dl2050utils.egg-info/top_level.txt
test/test_core.py
test/test_db.py
test/test_env.py