Metadata-Version: 2.1
Name: dl2050utils
Version: 1.0.701
Summary: Utils lib
Author: João Neto
Author-email: joao.filipe.neto@gmail.com
License: MIT
Keywords: utils
Classifier: Development Status :: 4 - Beta
Classifier: Intended Audience :: Developers
Classifier: Topic :: Software Development :: Build Tools
Classifier: License :: OSI Approved :: MIT License
Classifier: Programming Language :: Python :: 3.7
License-File: LICENSE.txt
